easemlclient/__init__.py
easemlclient/model/__init__.py
easemlclient/model/common.py
easemlclient/model/core.py
easemlclient/model/dataset.py
easemlclient/model/job.py
easemlclient/model/module.py
easemlclient/model/process.py
easemlclient/model/task.py
easemlclient/model/type.py
easemlclient/model/user.py
easemlclient-0.1.13.dist-info/LICENCE
easemlclient-0.1.13.dist-info/METADATA
easemlclient-0.1.13.dist-info/WHEEL
easemlclient-0.1.13.dist-info/top_level.txt
easemlclient-0.1.13.dist-info/RECORD
